common/__init__.py
moniotor_rule_scripts/__init__.py
moniotor_rule_scripts/check_die_count_between_mes_raw.py
moniotor_rule_scripts/sbl_test.py
chandler_test-1.1.dist-info/METADATA
chandler_test-1.1.dist-info/WHEEL
chandler_test-1.1.dist-info/top_level.txt
chandler_test-1.1.dist-info/RECORD
